{
  "conceptSetId": 291,
  "vocabularyVersion": null,
  "resolvedConcepts": [
    {
      "conceptId": 4161814,
      "conceptName": "Peripherally inserted central catheter",
      "vocabularyId": "SNOMED",
      "domainId": "Device",
      "conceptClassId": "Physical Object",
      "conceptCode": "398176008",
      "standardConcept": "S"
    },
    {
      "conceptId": 4179206,
      "conceptName": "Central venous catheter",
      "vocabularyId": "SNOMED",
      "domainId": "Device",
      "conceptClassId": "Physical Object",
      "conceptCode": "52124006",
      "standardConcept": "S"
    },
    {
      "conceptId": 37167492,
      "conceptName": "Umbilical venous catheter",
      "vocabularyId": "SNOMED",
      "domainId": "Device",
      "conceptClassId": "Physical Object",
      "conceptCode": "1268297002",
      "standardConcept": "S"
    },
    {
      "conceptId": 37167946,
      "conceptName": "Epicutaneo-caval catheter",
      "vocabularyId": "SNOMED",
      "domainId": "Device",
      "conceptClassId": "Physical Object",
      "conceptCode": "1269192008",
      "standardConcept": "S"
    },
    {
      "conceptId": 40482049,
      "conceptName": "Tunneled central venous catheter",
      "vocabularyId": "SNOMED",
      "domainId": "Device",
      "conceptClassId": "Physical Object",
      "conceptCode": "445085009",
      "standardConcept": "S"
    },
    {
      "conceptId": 42709987,
      "conceptName": "Nontunneled central venous catheter",
      "vocabularyId": "SNOMED",
      "domainId": "Device",
      "conceptClassId": "Physical Object",
      "conceptCode": "449859004",
      "standardConcept": "S"
    },
    {
      "conceptId": 42709989,
      "conceptName": "Cuffed central venous catheter",
      "vocabularyId": "SNOMED",
      "domainId": "Device",
      "conceptClassId": "Physical Object",
      "conceptCode": "449861008",
      "standardConcept": "S"
    }
  ]
}