{
  "conceptSetId": 303,
  "vocabularyVersion": null,
  "resolvedConcepts": [
    {
      "conceptId": 4012607,
      "conceptName": "Removal of tracheostomy tube",
      "vocabularyId": "SNOMED",
      "domainId": "Procedure",
      "conceptClassId": "Procedure",
      "conceptCode": "113153002",
      "standardConcept": "S"
    },
    {
      "conceptId": 4148972,
      "conceptName": "Extubation of trachea",
      "vocabularyId": "SNOMED",
      "domainId": "Procedure",
      "conceptClassId": "Procedure",
      "conceptCode": "309812005",
      "standardConcept": "S"
    },
    {
      "conceptId": 4150627,
      "conceptName": "Removal of endotracheal tube",
      "vocabularyId": "SNOMED",
      "domainId": "Procedure",
      "conceptClassId": "Procedure",
      "conceptCode": "271280005",
      "standardConcept": "S"
    },
    {
      "conceptId": 4195943,
      "conceptName": "Ventilating tube removal by another physician",
      "vocabularyId": "SNOMED",
      "domainId": "Procedure",
      "conceptClassId": "Procedure",
      "conceptCode": "44482009",
      "standardConcept": "S"
    },
    {
      "conceptId": 4231838,
      "conceptName": "Inadvertent tracheal extubation",
      "vocabularyId": "SNOMED",
      "domainId": "Observation",
      "conceptClassId": "Clinical Finding",
      "conceptCode": "405639008",
      "standardConcept": "S"
    }
  ]
}