{
  "id": 136,
  "name": "Propofol",
  "description": null,
  "version": "1.0.0",
  "createdBy": "Boris Delange",
  "createdDate": "2025-01-26",
  "modifiedBy": "Boris Delange",
  "modifiedDate": "2025-01-26",
  "createdByTool": "INDICATE Data Dictionary v0.2.0.9001",
  "expression": {
    "items": [
      {
        "concept": {
          "conceptId": 40834464,
          "conceptName": "Concept 40834464",
          "standardConcept": "S",
          "standardConceptCaption": "Standard",
          "invalidReason": null,
          "invalidReasonCaption": "Valid",
          "conceptCode": "",
          "domainId": "",
          "vocabularyId": "",
          "conceptClassId": "",
          "validStartDate": "1970-01-01",
          "validEndDate": "2099-12-31"
        },
        "isExcluded": false,
        "includeDescendants": false,
        "includeMapped": false
      },
      {
        "concept": {
          "conceptId": 40865591,
          "conceptName": "Concept 40865591",
          "standardConcept": "S",
          "standardConceptCaption": "Standard",
          "invalidReason": null,
          "invalidReasonCaption": "Valid",
          "conceptCode": "",
          "domainId": "",
          "vocabularyId": "",
          "conceptClassId": "",
          "validStartDate": "1970-01-01",
          "validEndDate": "2099-12-31"
        },
        "isExcluded": false,
        "includeDescendants": false,
        "includeMapped": false
      },
      {
        "concept": {
          "conceptId": 40896767,
          "conceptName": "Concept 40896767",
          "standardConcept": "S",
          "standardConceptCaption": "Standard",
          "invalidReason": null,
          "invalidReasonCaption": "Valid",
          "conceptCode": "",
          "domainId": "",
          "vocabularyId": "",
          "conceptClassId": "",
          "validStartDate": "1970-01-01",
          "validEndDate": "2099-12-31"
        },
        "isExcluded": false,
        "includeDescendants": false,
        "includeMapped": false
      },
      {
        "concept": {
          "conceptId": 44176115,
          "conceptName": "Concept 44176115",
          "standardConcept": "S",
          "standardConceptCaption": "Standard",
          "invalidReason": null,
          "invalidReasonCaption": "Valid",
          "conceptCode": "",
          "domainId": "",
          "vocabularyId": "",
          "conceptClassId": "",
          "validStartDate": "1970-01-01",
          "validEndDate": "2099-12-31"
        },
        "isExcluded": false,
        "includeDescendants": false,
        "includeMapped": false
      },
      {
        "concept": {
          "conceptId": 43679557,
          "conceptName": "Concept 43679557",
          "standardConcept": "S",
          "standardConceptCaption": "Standard",
          "invalidReason": null,
          "invalidReasonCaption": "Valid",
          "conceptCode": "",
          "domainId": "",
          "vocabularyId": "",
          "conceptClassId": "",
          "validStartDate": "1970-01-01",
          "validEndDate": "2099-12-31"
        },
        "isExcluded": false,
        "includeDescendants": false,
        "includeMapped": false
      },
      {
        "concept": {
          "conceptId": 43751294,
          "conceptName": "Concept 43751294",
          "standardConcept": "S",
          "standardConceptCaption": "Standard",
          "invalidReason": null,
          "invalidReasonCaption": "Valid",
          "conceptCode": "",
          "domainId": "",
          "vocabularyId": "",
          "conceptClassId": "",
          "validStartDate": "1970-01-01",
          "validEndDate": "2099-12-31"
        },
        "isExcluded": false,
        "includeDescendants": false,
        "includeMapped": false
      },
      {
        "concept": {
          "conceptId": 753627,
          "conceptName": "Concept 753627",
          "standardConcept": "S",
          "standardConceptCaption": "Standard",
          "invalidReason": null,
          "invalidReasonCaption": "Valid",
          "conceptCode": "",
          "domainId": "",
          "vocabularyId": "",
          "conceptClassId": "",
          "validStartDate": "1970-01-01",
          "validEndDate": "2099-12-31"
        },
        "isExcluded": false,
        "includeDescendants": false,
        "includeMapped": false
      },
      {
        "concept": {
          "conceptId": 40220389,
          "conceptName": "Concept 40220389",
          "standardConcept": "S",
          "standardConceptCaption": "Standard",
          "invalidReason": null,
          "invalidReasonCaption": "Valid",
          "conceptCode": "",
          "domainId": "",
          "vocabularyId": "",
          "conceptClassId": "",
          "validStartDate": "1970-01-01",
          "validEndDate": "2099-12-31"
        },
        "isExcluded": false,
        "includeDescendants": false,
        "includeMapped": false
      },
      {
        "concept": {
          "conceptId": 1145814,
          "conceptName": "Concept 1145814",
          "standardConcept": "S",
          "standardConceptCaption": "Standard",
          "invalidReason": null,
          "invalidReasonCaption": "Valid",
          "conceptCode": "",
          "domainId": "",
          "vocabularyId": "",
          "conceptClassId": "",
          "validStartDate": "1970-01-01",
          "validEndDate": "2099-12-31"
        },
        "isExcluded": false,
        "includeDescendants": false,
        "includeMapped": false
      },
      {
        "concept": {
          "conceptId": 1537217,
          "conceptName": "Concept 1537217",
          "standardConcept": "S",
          "standardConceptCaption": "Standard",
          "invalidReason": null,
          "invalidReasonCaption": "Valid",
          "conceptCode": "",
          "domainId": "",
          "vocabularyId": "",
          "conceptClassId": "",
          "validStartDate": "1970-01-01",
          "validEndDate": "2099-12-31"
        },
        "isExcluded": false,
        "includeDescendants": false,
        "includeMapped": false
      },
      {
        "concept": {
          "conceptId": 1537391,
          "conceptName": "Concept 1537391",
          "standardConcept": "S",
          "standardConceptCaption": "Standard",
          "invalidReason": null,
          "invalidReasonCaption": "Valid",
          "conceptCode": "",
          "domainId": "",
          "vocabularyId": "",
          "conceptClassId": "",
          "validStartDate": "1970-01-01",
          "validEndDate": "2099-12-31"
        },
        "isExcluded": false,
        "includeDescendants": false,
        "includeMapped": false
      },
      {
        "concept": {
          "conceptId": 753629,
          "conceptName": "Concept 753629",
          "standardConcept": "S",
          "standardConceptCaption": "Standard",
          "invalidReason": null,
          "invalidReasonCaption": "Valid",
          "conceptCode": "",
          "domainId": "",
          "vocabularyId": "",
          "conceptClassId": "",
          "validStartDate": "1970-01-01",
          "validEndDate": "2099-12-31"
        },
        "isExcluded": false,
        "includeDescendants": false,
        "includeMapped": false
      },
      {
        "concept": {
          "conceptId": 43820937,
          "conceptName": "Concept 43820937",
          "standardConcept": "S",
          "standardConceptCaption": "Standard",
          "invalidReason": null,
          "invalidReasonCaption": "Valid",
          "conceptCode": "",
          "domainId": "",
          "vocabularyId": "",
          "conceptClassId": "",
          "validStartDate": "1970-01-01",
          "validEndDate": "2099-12-31"
        },
        "isExcluded": false,
        "includeDescendants": false,
        "includeMapped": false
      },
      {
        "concept": {
          "conceptId": 43820942,
          "conceptName": "Concept 43820942",
          "standardConcept": "S",
          "standardConceptCaption": "Standard",
          "invalidReason": null,
          "invalidReasonCaption": "Valid",
          "conceptCode": "",
          "domainId": "",
          "vocabularyId": "",
          "conceptClassId": "",
          "validStartDate": "1970-01-01",
          "validEndDate": "2099-12-31"
        },
        "isExcluded": false,
        "includeDescendants": false,
        "includeMapped": false
      },
      {
        "concept": {
          "conceptId": 40990300,
          "conceptName": "Concept 40990300",
          "standardConcept": "S",
          "standardConceptCaption": "Standard",
          "invalidReason": null,
          "invalidReasonCaption": "Valid",
          "conceptCode": "",
          "domainId": "",
          "vocabularyId": "",
          "conceptClassId": "",
          "validStartDate": "1970-01-01",
          "validEndDate": "2099-12-31"
        },
        "isExcluded": false,
        "includeDescendants": false,
        "includeMapped": false
      },
      {
        "concept": {
          "conceptId": 41052470,
          "conceptName": "Concept 41052470",
          "standardConcept": "S",
          "standardConceptCaption": "Standard",
          "invalidReason": null,
          "invalidReasonCaption": "Valid",
          "conceptCode": "",
          "domainId": "",
          "vocabularyId": "",
          "conceptClassId": "",
          "validStartDate": "1970-01-01",
          "validEndDate": "2099-12-31"
        },
        "isExcluded": false,
        "includeDescendants": false,
        "includeMapped": false
      },
      {
        "concept": {
          "conceptId": 21044754,
          "conceptName": "Concept 21044754",
          "standardConcept": "S",
          "standardConceptCaption": "Standard",
          "invalidReason": null,
          "invalidReasonCaption": "Valid",
          "conceptCode": "",
          "domainId": "",
          "vocabularyId": "",
          "conceptClassId": "",
          "validStartDate": "1970-01-01",
          "validEndDate": "2099-12-31"
        },
        "isExcluded": false,
        "includeDescendants": false,
        "includeMapped": false
      },
      {
        "concept": {
          "conceptId": 44071160,
          "conceptName": "Concept 44071160",
          "standardConcept": "S",
          "standardConceptCaption": "Standard",
          "invalidReason": null,
          "invalidReasonCaption": "Valid",
          "conceptCode": "",
          "domainId": "",
          "vocabularyId": "",
          "conceptClassId": "",
          "validStartDate": "1970-01-01",
          "validEndDate": "2099-12-31"
        },
        "isExcluded": false,
        "includeDescendants": false,
        "includeMapped": false
      },
      {
        "concept": {
          "conceptId": 41240274,
          "conceptName": "Concept 41240274",
          "standardConcept": "S",
          "standardConceptCaption": "Standard",
          "invalidReason": null,
          "invalidReasonCaption": "Valid",
          "conceptCode": "",
          "domainId": "",
          "vocabularyId": "",
          "conceptClassId": "",
          "validStartDate": "1970-01-01",
          "validEndDate": "2099-12-31"
        },
        "isExcluded": false,
        "includeDescendants": false,
        "includeMapped": false
      },
      {
        "concept": {
          "conceptId": 41271144,
          "conceptName": "Concept 41271144",
          "standardConcept": "S",
          "standardConceptCaption": "Standard",
          "invalidReason": null,
          "invalidReasonCaption": "Valid",
          "conceptCode": "",
          "domainId": "",
          "vocabularyId": "",
          "conceptClassId": "",
          "validStartDate": "1970-01-01",
          "validEndDate": "2099-12-31"
        },
        "isExcluded": false,
        "includeDescendants": false,
        "includeMapped": false
      },
      {
        "concept": {
          "conceptId": 41271145,
          "conceptName": "Concept 41271145",
          "standardConcept": "S",
          "standardConceptCaption": "Standard",
          "invalidReason": null,
          "invalidReasonCaption": "Valid",
          "conceptCode": "",
          "domainId": "",
          "vocabularyId": "",
          "conceptClassId": "",
          "validStartDate": "1970-01-01",
          "validEndDate": "2099-12-31"
        },
        "isExcluded": false,
        "includeDescendants": false,
        "includeMapped": false
      },
      {
        "concept": {
          "conceptId": 36882820,
          "conceptName": "Concept 36882820",
          "standardConcept": "S",
          "standardConceptCaption": "Standard",
          "invalidReason": null,
          "invalidReasonCaption": "Valid",
          "conceptCode": "",
          "domainId": "",
          "vocabularyId": "",
          "conceptClassId": "",
          "validStartDate": "1970-01-01",
          "validEndDate": "2099-12-31"
        },
        "isExcluded": false,
        "includeDescendants": false,
        "includeMapped": false
      },
      {
        "concept": {
          "conceptId": 35864285,
          "conceptName": "Concept 35864285",
          "standardConcept": "S",
          "standardConceptCaption": "Standard",
          "invalidReason": null,
          "invalidReasonCaption": "Valid",
          "conceptCode": "",
          "domainId": "",
          "vocabularyId": "",
          "conceptClassId": "",
          "validStartDate": "1970-01-01",
          "validEndDate": "2099-12-31"
        },
        "isExcluded": false,
        "includeDescendants": false,
        "includeMapped": false
      },
      {
        "concept": {
          "conceptId": 2915382,
          "conceptName": "Concept 2915382",
          "standardConcept": "S",
          "standardConceptCaption": "Standard",
          "invalidReason": null,
          "invalidReasonCaption": "Valid",
          "conceptCode": "",
          "domainId": "",
          "vocabularyId": "",
          "conceptClassId": "",
          "validStartDate": "1970-01-01",
          "validEndDate": "2099-12-31"
        },
        "isExcluded": false,
        "includeDescendants": false,
        "includeMapped": false
      }
    ]
  },
  "tags": [],
  "metadata": {
    "translations": {
      "en": {
        "name": "Propofol",
        "category": "Drug",
        "subcategory": "Sedative drugs"
      },
      "fr": {
        "name": "Propofol",
        "category": "Traitements",
        "subcategory": "Sédatifs"
      }
    },
    "createdByDetails": {
      "firstName": "Boris",
      "lastName": "Delange",
      "affiliation": "Univ Rennes, CHU Rennes, INSERM, LTSI-UMR 1099, Rennes, France",
      "profession": "Medical Informatics and Intensive Care Physician",
      "orcid": "0009-0002-6055-6935"
    },
    "reviews": [],
    "versions": [],
    "distributionStats": null
  }
}
