{
  "id": 254,
  "name": "[Deprecated] Serratia (genus)",
  "description": "Deprecated — genus-level set too broad; overlaps the species sets. Use the species-specific Serratia sets (e.g. Serratia marcescens, Serratia liquefaciens) instead.",
  "version": "1.1.0",
  "createdBy": "Boris Delange",
  "createdDate": "2026-02-12",
  "modifiedBy": "Boris Delange",
  "modifiedDate": "2026-06-11",
  "createdByTool": "INDICATE Data Dictionary (Web) v1.0.0",
  "expression": {
    "items": [
      {
        "concept": {
          "conceptId": 1242264,
          "conceptName": "Extended spectrum beta-lactamase producing Serratia fonticola",
          "domainId": "Observation",
          "vocabularyId": "SNOMED",
          "conceptClassId": "Organism",
          "standardConcept": "S",
          "standardConceptCaption": "Standard",
          "conceptCode": "1106701000112108",
          "validStartDate": "2023-11-01",
          "validEndDate": "2099-12-31",
          "invalidReason": null,
          "invalidReasonCaption": "Valid"
        },
        "isExcluded": false,
        "includeDescendants": false,
        "includeMapped": false
      },
      {
        "concept": {
          "conceptId": 1242266,
          "conceptName": "Extended spectrum beta-lactamase producing Serratia liquefaciens",
          "domainId": "Observation",
          "vocabularyId": "SNOMED",
          "conceptClassId": "Organism",
          "standardConcept": "S",
          "standardConceptCaption": "Standard",
          "conceptCode": "1107101000112105",
          "validStartDate": "2023-11-01",
          "validEndDate": "2099-12-31",
          "invalidReason": null,
          "invalidReasonCaption": "Valid"
        },
        "isExcluded": false,
        "includeDescendants": false,
        "includeMapped": false
      },
      {
        "concept": {
          "conceptId": 3657175,
          "conceptName": "Carbapenemase-producing Serratia marcescens",
          "domainId": "Observation",
          "vocabularyId": "SNOMED",
          "conceptClassId": "Organism",
          "standardConcept": "S",
          "standardConceptCaption": "Standard",
          "conceptCode": "1107201000112104",
          "validStartDate": "2020-07-31",
          "validEndDate": "2099-12-31",
          "invalidReason": null,
          "invalidReasonCaption": "Valid"
        },
        "isExcluded": false,
        "includeDescendants": false,
        "includeMapped": false
      },
      {
        "concept": {
          "conceptId": 4011216,
          "conceptName": "Serratia fonticola",
          "domainId": "Observation",
          "vocabularyId": "SNOMED",
          "conceptClassId": "Organism",
          "standardConcept": "S",
          "standardConceptCaption": "Standard",
          "conceptCode": "112329006",
          "validStartDate": "2002-01-31",
          "validEndDate": "2099-12-31",
          "invalidReason": null,
          "invalidReasonCaption": "Valid"
        },
        "isExcluded": false,
        "includeDescendants": false,
        "includeMapped": false
      },
      {
        "concept": {
          "conceptId": 4015918,
          "conceptName": "Serratia grimesii",
          "domainId": "Observation",
          "vocabularyId": "SNOMED",
          "conceptClassId": "Organism",
          "standardConcept": "S",
          "standardConceptCaption": "Standard",
          "conceptCode": "115005002",
          "validStartDate": "2002-01-31",
          "validEndDate": "2099-12-31",
          "invalidReason": null,
          "invalidReasonCaption": "Valid"
        },
        "isExcluded": false,
        "includeDescendants": false,
        "includeMapped": false
      },
      {
        "concept": {
          "conceptId": 4016238,
          "conceptName": "Serratia odorifera",
          "domainId": "Observation",
          "vocabularyId": "SNOMED",
          "conceptClassId": "Organism",
          "standardConcept": "S",
          "standardConceptCaption": "Standard",
          "conceptCode": "10413007",
          "validStartDate": "2002-01-31",
          "validEndDate": "2099-12-31",
          "invalidReason": null,
          "invalidReasonCaption": "Valid"
        },
        "isExcluded": false,
        "includeDescendants": false,
        "includeMapped": false
      },
      {
        "concept": {
          "conceptId": 4018272,
          "conceptName": "Serratia marcescens, Biogroup I",
          "domainId": "Observation",
          "vocabularyId": "SNOMED",
          "conceptClassId": "Organism",
          "standardConcept": "S",
          "standardConceptCaption": "Standard",
          "conceptCode": "115006001",
          "validStartDate": "2002-01-31",
          "validEndDate": "2099-12-31",
          "invalidReason": null,
          "invalidReasonCaption": "Valid"
        },
        "isExcluded": false,
        "includeDescendants": false,
        "includeMapped": false
      },
      {
        "concept": {
          "conceptId": 4018785,
          "conceptName": "Serratia proteamaculans subsp quinovora",
          "domainId": "Observation",
          "vocabularyId": "SNOMED",
          "conceptClassId": "Organism",
          "standardConcept": "S",
          "standardConceptCaption": "Standard",
          "conceptCode": "115004003",
          "validStartDate": "2002-01-31",
          "validEndDate": "2099-12-31",
          "invalidReason": null,
          "invalidReasonCaption": "Valid"
        },
        "isExcluded": false,
        "includeDescendants": false,
        "includeMapped": false
      },
      {
        "concept": {
          "conceptId": 4019095,
          "conceptName": "Serratia proteamaculans",
          "domainId": "Observation",
          "vocabularyId": "SNOMED",
          "conceptClassId": "Organism",
          "standardConcept": "S",
          "standardConceptCaption": "Standard",
          "conceptCode": "116135003",
          "validStartDate": "2002-01-31",
          "validEndDate": "2099-12-31",
          "invalidReason": null,
          "invalidReasonCaption": "Valid"
        },
        "isExcluded": false,
        "includeDescendants": false,
        "includeMapped": false
      },
      {
        "concept": {
          "conceptId": 4021525,
          "conceptName": "Serratia proteamaculans subsp proteamaculans",
          "domainId": "Observation",
          "vocabularyId": "SNOMED",
          "conceptClassId": "Organism",
          "standardConcept": "S",
          "standardConceptCaption": "Standard",
          "conceptCode": "116136002",
          "validStartDate": "2002-01-31",
          "validEndDate": "2099-12-31",
          "invalidReason": null,
          "invalidReasonCaption": "Valid"
        },
        "isExcluded": false,
        "includeDescendants": false,
        "includeMapped": false
      },
      {
        "concept": {
          "conceptId": 4028952,
          "conceptName": "Serratia liquefaciens",
          "domainId": "Observation",
          "vocabularyId": "SNOMED",
          "conceptClassId": "Organism",
          "standardConcept": "S",
          "standardConceptCaption": "Standard",
          "conceptCode": "23787004",
          "validStartDate": "2002-01-31",
          "validEndDate": "2099-12-31",
          "invalidReason": null,
          "invalidReasonCaption": "Valid"
        },
        "isExcluded": false,
        "includeDescendants": false,
        "includeMapped": false
      },
      {
        "concept": {
          "conceptId": 4104185,
          "conceptName": "Serratia plymuthica",
          "domainId": "Observation",
          "vocabularyId": "SNOMED",
          "conceptClassId": "Organism",
          "standardConcept": "S",
          "standardConceptCaption": "Standard",
          "conceptCode": "28955009",
          "validStartDate": "2002-01-31",
          "validEndDate": "2099-12-31",
          "invalidReason": null,
          "invalidReasonCaption": "Valid"
        },
        "isExcluded": false,
        "includeDescendants": false,
        "includeMapped": false
      },
      {
        "concept": {
          "conceptId": 4140691,
          "conceptName": "Serratia marcescens",
          "domainId": "Observation",
          "vocabularyId": "SNOMED",
          "conceptClassId": "Organism",
          "standardConcept": "S",
          "standardConceptCaption": "Standard",
          "conceptCode": "33522002",
          "validStartDate": "2002-01-31",
          "validEndDate": "2099-12-31",
          "invalidReason": null,
          "invalidReasonCaption": "Valid"
        },
        "isExcluded": false,
        "includeDescendants": false,
        "includeMapped": false
      },
      {
        "concept": {
          "conceptId": 4170580,
          "conceptName": "Serratia",
          "domainId": "Observation",
          "vocabularyId": "SNOMED",
          "conceptClassId": "Organism",
          "standardConcept": "S",
          "standardConceptCaption": "Standard",
          "conceptCode": "42025004",
          "validStartDate": "2002-01-31",
          "validEndDate": "2099-12-31",
          "invalidReason": null,
          "invalidReasonCaption": "Valid"
        },
        "isExcluded": false,
        "includeDescendants": false,
        "includeMapped": false
      },
      {
        "concept": {
          "conceptId": 4183695,
          "conceptName": "Serratia rubidaea",
          "domainId": "Observation",
          "vocabularyId": "SNOMED",
          "conceptClassId": "Organism",
          "standardConcept": "S",
          "standardConceptCaption": "Standard",
          "conceptCode": "55825002",
          "validStartDate": "2002-01-31",
          "validEndDate": "2099-12-31",
          "invalidReason": null,
          "invalidReasonCaption": "Valid"
        },
        "isExcluded": false,
        "includeDescendants": false,
        "includeMapped": false
      },
      {
        "concept": {
          "conceptId": 4198204,
          "conceptName": "Serratia ficaria",
          "domainId": "Observation",
          "vocabularyId": "SNOMED",
          "conceptClassId": "Organism",
          "standardConcept": "S",
          "standardConceptCaption": "Standard",
          "conceptCode": "802004",
          "validStartDate": "2002-01-31",
          "validEndDate": "2099-12-31",
          "invalidReason": null,
          "invalidReasonCaption": "Valid"
        },
        "isExcluded": false,
        "includeDescendants": false,
        "includeMapped": false
      },
      {
        "concept": {
          "conceptId": 4207914,
          "conceptName": "Serratia marcescens marcescens",
          "domainId": "Observation",
          "vocabularyId": "SNOMED",
          "conceptClassId": "Organism",
          "standardConcept": "S",
          "standardConceptCaption": "Standard",
          "conceptCode": "438911005",
          "validStartDate": "2009-01-31",
          "validEndDate": "2099-12-31",
          "invalidReason": null,
          "invalidReasonCaption": "Valid"
        },
        "isExcluded": false,
        "includeDescendants": false,
        "includeMapped": false
      },
      {
        "concept": {
          "conceptId": 4230550,
          "conceptName": "Serratia marcescens sakuensis",
          "domainId": "Observation",
          "vocabularyId": "SNOMED",
          "conceptClassId": "Organism",
          "standardConcept": "S",
          "standardConceptCaption": "Standard",
          "conceptCode": "438912003",
          "validStartDate": "2009-01-31",
          "validEndDate": "2099-12-31",
          "invalidReason": null,
          "invalidReasonCaption": "Valid"
        },
        "isExcluded": false,
        "includeDescendants": false,
        "includeMapped": false
      },
      {
        "concept": {
          "conceptId": 4231049,
          "conceptName": "Serratia quinivorans",
          "domainId": "Observation",
          "vocabularyId": "SNOMED",
          "conceptClassId": "Organism",
          "standardConcept": "S",
          "standardConceptCaption": "Standard",
          "conceptCode": "438199009",
          "validStartDate": "2009-01-31",
          "validEndDate": "2099-12-31",
          "invalidReason": null,
          "invalidReasonCaption": "Valid"
        },
        "isExcluded": false,
        "includeDescendants": false,
        "includeMapped": false
      },
      {
        "concept": {
          "conceptId": 4264130,
          "conceptName": "Serratia odorifera biogroup 2",
          "domainId": "Observation",
          "vocabularyId": "SNOMED",
          "conceptClassId": "Organism",
          "standardConcept": "S",
          "standardConceptCaption": "Standard",
          "conceptCode": "397076008",
          "validStartDate": "2003-07-31",
          "validEndDate": "2099-12-31",
          "invalidReason": null,
          "invalidReasonCaption": "Valid"
        },
        "isExcluded": false,
        "includeDescendants": false,
        "includeMapped": false
      },
      {
        "concept": {
          "conceptId": 4287331,
          "conceptName": "Serratia odorifera biogroup 1",
          "domainId": "Observation",
          "vocabularyId": "SNOMED",
          "conceptClassId": "Organism",
          "standardConcept": "S",
          "standardConceptCaption": "Standard",
          "conceptCode": "397075007",
          "validStartDate": "2003-07-31",
          "validEndDate": "2099-12-31",
          "invalidReason": null,
          "invalidReasonCaption": "Valid"
        },
        "isExcluded": false,
        "includeDescendants": false,
        "includeMapped": false
      },
      {
        "concept": {
          "conceptId": 4297293,
          "conceptName": "Serratia entomophila",
          "domainId": "Observation",
          "vocabularyId": "SNOMED",
          "conceptClassId": "Organism",
          "standardConcept": "S",
          "standardConceptCaption": "Standard",
          "conceptCode": "76656001",
          "validStartDate": "2002-01-31",
          "validEndDate": "2099-12-31",
          "invalidReason": null,
          "invalidReasonCaption": "Valid"
        },
        "isExcluded": false,
        "includeDescendants": false,
        "includeMapped": false
      },
      {
        "concept": {
          "conceptId": 36713847,
          "conceptName": "Serratia vespertilionis",
          "domainId": "Observation",
          "vocabularyId": "SNOMED",
          "conceptClassId": "Organism",
          "standardConcept": "S",
          "standardConceptCaption": "Standard",
          "conceptCode": "718823003",
          "validStartDate": "2017-01-31",
          "validEndDate": "2099-12-31",
          "invalidReason": null,
          "invalidReasonCaption": "Valid"
        },
        "isExcluded": false,
        "includeDescendants": false,
        "includeMapped": false
      },
      {
        "concept": {
          "conceptId": 36716295,
          "conceptName": "Serratia liquefaciens complex",
          "domainId": "Observation",
          "vocabularyId": "SNOMED",
          "conceptClassId": "Organism",
          "standardConcept": "S",
          "standardConceptCaption": "Standard",
          "conceptCode": "722258003",
          "validStartDate": "2017-01-31",
          "validEndDate": "2099-12-31",
          "invalidReason": null,
          "invalidReasonCaption": "Valid"
        },
        "isExcluded": false,
        "includeDescendants": false,
        "includeMapped": false
      },
      {
        "concept": {
          "conceptId": 37151813,
          "conceptName": "Extended spectrum beta-lactamase producing Serratia marcescens",
          "domainId": "Observation",
          "vocabularyId": "SNOMED",
          "conceptClassId": "Organism",
          "standardConcept": "S",
          "standardConceptCaption": "Standard",
          "conceptCode": "1107301000112107",
          "validStartDate": "2023-05-31",
          "validEndDate": "2099-12-31",
          "invalidReason": null,
          "invalidReasonCaption": "Valid"
        },
        "isExcluded": false,
        "includeDescendants": false,
        "includeMapped": false
      },
      {
        "concept": {
          "conceptId": 37156031,
          "conceptName": "Extended spectrum beta-lactamase producing Serratia",
          "domainId": "Observation",
          "vocabularyId": "SNOMED",
          "conceptClassId": "Organism",
          "standardConcept": "S",
          "standardConceptCaption": "Standard",
          "conceptCode": "1106301000112109",
          "validStartDate": "2023-05-31",
          "validEndDate": "2099-12-31",
          "invalidReason": null,
          "invalidReasonCaption": "Valid"
        },
        "isExcluded": false,
        "includeDescendants": false,
        "includeMapped": false
      },
      {
        "concept": {
          "conceptId": 37156032,
          "conceptName": "Carbapenemase-producing Serratia fonticola",
          "domainId": "Observation",
          "vocabularyId": "SNOMED",
          "conceptClassId": "Organism",
          "standardConcept": "S",
          "standardConceptCaption": "Standard",
          "conceptCode": "1106601000112104",
          "validStartDate": "2023-04-30",
          "validEndDate": "2099-12-31",
          "invalidReason": null,
          "invalidReasonCaption": "Valid"
        },
        "isExcluded": false,
        "includeDescendants": false,
        "includeMapped": false
      },
      {
        "concept": {
          "conceptId": 37156033,
          "conceptName": "Extended spectrum beta-lactamase producing Serratia odorifera",
          "domainId": "Observation",
          "vocabularyId": "SNOMED",
          "conceptClassId": "Organism",
          "standardConcept": "S",
          "standardConceptCaption": "Standard",
          "conceptCode": "1107501000112101",
          "validStartDate": "2023-05-31",
          "validEndDate": "2099-12-31",
          "invalidReason": null,
          "invalidReasonCaption": "Valid"
        },
        "isExcluded": false,
        "includeDescendants": false,
        "includeMapped": false
      },
      {
        "concept": {
          "conceptId": 37156034,
          "conceptName": "Extended spectrum beta-lactamase producing Serratia plymuthica",
          "domainId": "Observation",
          "vocabularyId": "SNOMED",
          "conceptClassId": "Organism",
          "standardConcept": "S",
          "standardConceptCaption": "Standard",
          "conceptCode": "1107701000112106",
          "validStartDate": "2023-05-31",
          "validEndDate": "2099-12-31",
          "invalidReason": null,
          "invalidReasonCaption": "Valid"
        },
        "isExcluded": false,
        "includeDescendants": false,
        "includeMapped": false
      },
      {
        "concept": {
          "conceptId": 37159494,
          "conceptName": "Serratia myotis",
          "domainId": "Observation",
          "vocabularyId": "SNOMED",
          "conceptClassId": "Organism",
          "standardConcept": "S",
          "standardConceptCaption": "Standard",
          "conceptCode": "37081000087102",
          "validStartDate": "2022-12-31",
          "validEndDate": "2099-12-31",
          "invalidReason": null,
          "invalidReasonCaption": "Valid"
        },
        "isExcluded": false,
        "includeDescendants": false,
        "includeMapped": false
      },
      {
        "concept": {
          "conceptId": 37311342,
          "conceptName": "Carbapenem-resistant Serratia marcescens",
          "domainId": "Observation",
          "vocabularyId": "SNOMED",
          "conceptClassId": "Organism",
          "standardConcept": "S",
          "standardConceptCaption": "Standard",
          "conceptCode": "816049003",
          "validStartDate": "2020-01-31",
          "validEndDate": "2099-12-31",
          "invalidReason": null,
          "invalidReasonCaption": "Valid"
        },
        "isExcluded": false,
        "includeDescendants": false,
        "includeMapped": false
      },
      {
        "concept": {
          "conceptId": 37395793,
          "conceptName": "Multiple drug-resistant Serratia marcescens",
          "domainId": "Observation",
          "vocabularyId": "SNOMED",
          "conceptClassId": "Organism",
          "standardConcept": "S",
          "standardConceptCaption": "Standard",
          "conceptCode": "715354005",
          "validStartDate": "2016-07-31",
          "validEndDate": "2099-12-31",
          "invalidReason": null,
          "invalidReasonCaption": "Valid"
        },
        "isExcluded": false,
        "includeDescendants": false,
        "includeMapped": false
      },
      {
        "concept": {
          "conceptId": 42872424,
          "conceptName": "Serratia nematodiphila",
          "domainId": "Observation",
          "vocabularyId": "SNOMED",
          "conceptClassId": "Organism",
          "standardConcept": "S",
          "standardConceptCaption": "Standard",
          "conceptCode": "450415000",
          "validStartDate": "2012-07-31",
          "validEndDate": "2099-12-31",
          "invalidReason": null,
          "invalidReasonCaption": "Valid"
        },
        "isExcluded": false,
        "includeDescendants": false,
        "includeMapped": false
      },
      {
        "concept": {
          "conceptId": 42872425,
          "conceptName": "Serratia ureilytica",
          "domainId": "Observation",
          "vocabularyId": "SNOMED",
          "conceptClassId": "Organism",
          "standardConcept": "S",
          "standardConceptCaption": "Standard",
          "conceptCode": "450416004",
          "validStartDate": "2012-07-31",
          "validEndDate": "2099-12-31",
          "invalidReason": null,
          "invalidReasonCaption": "Valid"
        },
        "isExcluded": false,
        "includeDescendants": false,
        "includeMapped": false
      }
    ]
  },
  "tags": [],
  "metadata": {
    "uniqueId": "0c661deb-2ccf-475a-9a3b-febff6a58b8b",
    "organization": {
      "created": {
        "name": "INDICATE Consortium",
        "url": "https://indicate-eu.org"
      },
      "current": {
        "name": "INDICATE Consortium",
        "url": "https://indicate-eu.org"
      }
    },
    "sourceRepo": "https://github.com/indicate-eu/data-dictionary",
    "reviewStatus": "deprecated",
    "origin": null,
    "translations": {
      "en": {
        "name": "[Deprecated] Serratia (genus)",
        "category": "Microbiology",
        "subcategory": "Bacteria",
        "shortDescription": "Deprecated — genus-level set too broad; overlaps the species sets. Use the species-specific Serratia sets (e.g. Serratia marcescens, Serratia liquefaciens) instead.",
        "longDescription": null
      },
      "fr": {
        "name": "[Obsolète] Serratia (genre)",
        "category": "Microbiologie",
        "subcategory": "Bactéries",
        "shortDescription": "Obsolète — set au niveau genre trop large, chevauche les sets espèces. Utiliser les sets Serratia par espèce (ex. Serratia marcescens, Serratia liquefaciens).",
        "longDescription": null
      }
    },
    "createdByDetails": {
      "firstName": "Boris",
      "lastName": "Delange",
      "affiliation": "Univ Rennes, CHU Rennes, INSERM, LTSI-UMR 1099, Rennes, France",
      "profession": "Medical Informatics and Intensive Care Physician",
      "orcid": "0009-0002-6055-6935"
    },
    "reviews": [],
    "versions": [
      {
        "version": "1.1.0",
        "date": "2026-06-11",
        "author": "Boris Delange",
        "message": "Deprecated: genus-level Serratia set is too broad and overlaps the per-species Serratia sets. Use the species-specific sets instead."
      }
    ],
    "distributionStats": null
  }
}
