{
  "id": 147,
  "name": "Vasopressin",
  "description": null,
  "version": "1.0.0",
  "createdBy": "Boris Delange",
  "createdDate": "2025-01-26",
  "modifiedBy": "Boris Delange",
  "modifiedDate": "2025-01-26",
  "createdByTool": "INDICATE Data Dictionary v0.2.0.9001",
  "expression": {
    "items": []
  },
  "tags": [],
  "metadata": {
    "category": "Drug",
    "subcategory": "Vasoactive drugs",
    "mappingGuidance": null,
    "translations": {
      "en": {
        "name": "Vasopressin",
        "category": "Drug",
        "subcategory": "Vasoactive drugs"
      },
      "fr": {
        "name": "Vasopressin",
        "category": "Traitements",
        "subcategory": "Vasopresseurs"
      }
    },
    "createdByDetails": {
      "firstName": "Boris",
      "lastName": "Delange",
      "affiliation": "Univ Rennes, CHU Rennes, INSERM, LTSI-UMR 1099, Rennes, France",
      "profession": "Medical Informatics and Intensive Care Physician",
      "orcid": "0009-0002-6055-6935"
    },
    "reviews": [],
    "versions": [],
    "distributionStats": null
  }
}
